kb/__init__.py
kb.py-0.0.1.dist-info/METADATA
kb.py-0.0.1.dist-info/WHEEL
kb.py-0.0.1.dist-info/top_level.txt
kb.py-0.0.1.dist-info/zip-safe
kb.py-0.0.1.dist-info/RECORD
