Metadata-Version: 2.1
Name: kb.py
Version: 0.0.1
Summary: A util to enhance a keyboard
Home-page: https://github.com/xiongyihui/kb.py
Author: Yihui Xiong
Author-email: yihui.xiong@hotmail.com
License: UNKNOWN
Platform: UNKNOWN
Requires-Dist: keyboard
